acore_soap_app/__init__.py
acore_soap_app/_version.py
acore_soap_app/agent/__init__.py
acore_soap_app/agent/api.py
acore_soap_app/agent/execute-command.xml
acore_soap_app/agent/impl.py
acore_soap_app/api.py
acore_soap_app/cli/__init__.py
acore_soap_app/cli/impl.py
acore_soap_app/cli/main.py
acore_soap_app/docs/__init__.py
acore_soap_app/exc.py
acore_soap_app/paths.py
acore_soap_app/sdk/__init__.py
acore_soap_app/sdk/api.py
acore_soap_app/sdk/canned/__init__.py
acore_soap_app/sdk/canned/api.py
acore_soap_app/sdk/canned/impl.py
acore_soap_app/sdk/core.py
acore_soap_app/tests/__init__.py
acore_soap_app/tests/helper.py
acore_soap_app/tests/mock_aws.py
acore_soap_app/utils.py
acore_soap_app/vendor/__init__.py
acore_soap_app/vendor/pytest_cov_helper.py
acore_soap_app-0.3.7.dist-info/AUTHORS.rst
acore_soap_app-0.3.7.dist-info/LICENSE.txt
acore_soap_app-0.3.7.dist-info/METADATA
acore_soap_app-0.3.7.dist-info/WHEEL
acore_soap_app-0.3.7.dist-info/entry_points.txt
acore_soap_app-0.3.7.dist-info/RECORD
