Metadata-Version: 2.1
Name: acore_soap_app
Version: 0.3.7
Summary: Azerothcore World of Warcraft Soap Remote Access Python Library.
Home-page: https://github.com/MacHu-GWU/acore_soap_app-project
License: MIT
Author: Sanhe Hu
Author-email: husanhe@gmail.com
Maintainer: Sanhe Hu
Maintainer-email: husanhe@gmail.com
Requires-Python: >=3.8,<4.0
Classifier: Development Status :: 4 - Beta
Classifier: Intended Audience :: Developers
Classifier: License :: OSI Approved :: MIT License
Classifier: Natural Language :: English
Classifier: Operating System :: MacOS
Classifier: Operating System :: Microsoft :: Windows
Classifier: Operating System :: Unix
Classifier: Programming Language :: Python
Classifier: Programming Language :: Python :: 3
Classifier: Programming Language :: Python :: 3.8
Classifier: Programming Language :: Python :: 3.9
Classifier: Programming Language :: Python :: 3.10
Classifier: Programming Language :: Python :: 3.11
Classifier: Programming Language :: Python :: 3.12
Classifier: Programming Language :: Python :: 3 :: Only
Requires-Dist: acore_constants (>=0.2.1,<1.0.0)
Requires-Dist: acore_server_metadata (>=0.7.1,<2.0.0)
Requires-Dist: aws_ssm_run_command (>=1.0.1,<2.0.0)
Requires-Dist: boto_session_manager (>=1.7.2,<2.0.0)
Requires-Dist: fire (>=0.5.0,<1.0.0)
Requires-Dist: requests (>=2.20.0,<3.0.0)
Requires-Dist: simple_aws_ec2 (>=0.8.1,<1.0.0)
Requires-Dist: urllib3 (>=1.26.0,<2.0.0)
Project-URL: Documentation, https://acore-soap-app.readthedocs.io/en/latest/
